LICENSE
MANIFEST.in
Readme.md
setup.cfg
setup.py
XPySom.egg-info/PKG-INFO
XPySom.egg-info/SOURCES.txt
XPySom.egg-info/dependency_links.txt
XPySom.egg-info/not-zip-safe
XPySom.egg-info/requires.txt
XPySom.egg-info/top_level.txt
xpysom/__init__.py
xpysom/decays.py
xpysom/distances.py
xpysom/neighborhoods.py
xpysom/tests.py
xpysom/utils.py
xpysom/xpysom.py