Metadata-Version: 2.1
Name: XPySom
Version: 1.0.6
Summary: Minimalistic implementation of batch Self Organizing Maps (SOM) for parallel execution on CPU or GPU.
Home-page: https://github.com/Manciukic/xpysom
Author: Riccardo Mancini
Author-email: r.mancini@santannapisa.it
License: GNU General Public License v3.0
Download-URL: https://github.com/Manciukic/xpysom/archive/v1.0.5.tar.gz
Keywords: machine learning,neural networks,clustering,dimentionality reduction
Platform: UNKNOWN
Classifier: Development Status :: 4 - Beta
Classifier: Intended Audience :: Science/Research
Classifier: License :: OSI Approved :: GNU General Public License v3 (GPLv3)
Classifier: Programming Language :: Python :: 3
Classifier: Programming Language :: Python :: 3.4
Classifier: Programming Language :: Python :: 3.5
Classifier: Programming Language :: Python :: 3.6
Classifier: Programming Language :: Python :: 3.7
Classifier: Programming Language :: Python :: 3.8
Provides-Extra: cuda90
Provides-Extra: cuda92
Provides-Extra: cuda100
Provides-Extra: cuda101
Provides-Extra: cuda102
Provides-Extra: cuda110
Provides-Extra: cuda111
Provides-Extra: cuda112
